Metadata-Version: 1.1
Name: sandboxed
Version: 2.0
Summary: Sandbox/Virtual Machine detection
Home-page: https://github.com/frederikme/sandbox-evasion
Author: Frederik Mees
Author-email: frederik.mees@gmail.com
License: MIT
Download-URL: https://github.com/frederikme/sandbox-evasion/archive/2.0.tar.gz
Keywords: Sandbox,Virtual machine,Virtualbox,detection
Platform: UNKNOWN
Classifier: Development Status :: 3 - Alpha
Classifier: Intended Audience :: Developers
Classifier: Topic :: Software Development :: Build Tools
Classifier: License :: OSI Approved :: MIT License
Classifier: Programming Language :: Python :: 3
